ooz.abi3.so
pyooz-0.0.8.dist-info/RECORD
pyooz-0.0.8.dist-info/METADATA
pyooz-0.0.8.dist-info/top_level.txt
pyooz-0.0.8.dist-info/WHEEL
