Metadata-Version: 2.1
Name: pyooz
Version: 0.0.8
Summary: ooz decompression bindings
Classifier: Development Status :: 3 - Alpha
Classifier: License :: OSI Approved :: GNU General Public License v3 or later (GPLv3+)
Classifier: Natural Language :: English
Classifier: Programming Language :: Python :: 3 :: Only
